README.rst
setup.py
py/__init__.py
py/python_1.py
py/python_2.py
pyalisure.egg-info/PKG-INFO
pyalisure.egg-info/SOURCES.txt
pyalisure.egg-info/dependency_links.txt
pyalisure.egg-info/top_level.txt